LICENSE
README.md
setup.py
uro/__init__.py
uro/filters.py
uro/uro.py
uro/utils.py
uro.egg-info/PKG-INFO
uro.egg-info/SOURCES.txt
uro.egg-info/dependency_links.txt
uro.egg-info/entry_points.txt
uro.egg-info/top_level.txt