Metadata-Version: 2.2
Name: uro
Version: 1.0.2
Summary: A python tool to declutter url lists for crawling/pentesting
Home-page: https://github.com/s0md3v/uro
Download-URL: https://github.com/s0md3v/uro/archive/v1.0.2.zip
Author: s0md3v
License: Apache-2.0 License
Keywords: declutter,crawling,pentesting
Classifier: Topic :: Security
Classifier: Operating System :: OS Independent
Classifier: License :: OSI Approved :: Apache Software License
Classifier: Programming Language :: Python :: 3
License-File: LICENSE
Dynamic: author
Dynamic: classifier
Dynamic: description
Dynamic: description-content-type
Dynamic: download-url
Dynamic: home-page
Dynamic: keywords
Dynamic: license
Dynamic: summary
